Metadata-Version: 2.1
Name: openspacetrainenv
Version: 0.0.15
Summary: The OpenSpace train environment
Home-page: https://github.ugent.be/OpenSpace-DP/train_env
Author: OpenSpace
License: UNKNOWN
Platform: UNKNOWN
Classifier: Programming Language :: Python :: 3
Requires-Dist: nose (==1.3.7)
Requires-Dist: coverage (==4.5.2)
Requires-Dist: twisted (==18.9.0)
Requires-Dist: pyro4 (==4.75)
Requires-Dist: pika (==0.13.1)
Requires-Dist: requests (==2.21.0)
Requires-Dist: hyperlink (==18.0.0)
